mongodbbridge/__init__.py
mongodbbridge/mongo_main.py
mongodbbridge-0.0.7.dist-info/LICENSE
mongodbbridge-0.0.7.dist-info/METADATA
mongodbbridge-0.0.7.dist-info/WHEEL
mongodbbridge-0.0.7.dist-info/top_level.txt
mongodbbridge-0.0.7.dist-info/RECORD
